setup.py
pygameextra_cool_buttons/__base__.py
pygameextra_cool_buttons/__init__.py
pygameextra_cool_buttons/button_expansion.py
pygameextra_cool_buttons/buttons.py
pygameextra_cool_buttons/cb.py
pygameextra_cool_buttons/color.py
pygameextra_cool_buttons.egg-info/PKG-INFO
pygameextra_cool_buttons.egg-info/SOURCES.txt
pygameextra_cool_buttons.egg-info/dependency_links.txt
pygameextra_cool_buttons.egg-info/entry_points.txt
pygameextra_cool_buttons.egg-info/requires.txt
pygameextra_cool_buttons.egg-info/top_level.txt
pygameextra_cool_buttons_tester/IMAGE_A.png
pygameextra_cool_buttons_tester/IMAGE_B.png
pygameextra_cool_buttons_tester/__init__.py