Metadata-Version: 2.1
Name: pygameextra_cool_buttons
Version: 1.2.1
Summary: Pygameextra cool buttons is a extension for pygameextra that adds cool buttons
Author: Red
Author-email: redtonehair@gmail.com
Keywords: python
Requires-Dist: pygameextra>=2.0.0b45
Requires-Dist: Pillow
